odoo/addons/pos_receipt_replace_user_by_trigram_hr/README.rst
odoo/addons/pos_receipt_replace_user_by_trigram_hr/__init__.py
odoo/addons/pos_receipt_replace_user_by_trigram_hr/__manifest__.py
odoo/addons/pos_receipt_replace_user_by_trigram_hr/i18n/it.po
odoo/addons/pos_receipt_replace_user_by_trigram_hr/i18n/pos_receipt_replace_user_by_trigram_hr.pot
odoo/addons/pos_receipt_replace_user_by_trigram_hr/models/__init__.py
odoo/addons/pos_receipt_replace_user_by_trigram_hr/models/hr_employee.py
odoo/addons/pos_receipt_replace_user_by_trigram_hr/models/pos_session.py
odoo/addons/pos_receipt_replace_user_by_trigram_hr/readme/CONTRIBUTORS.rst
odoo/addons/pos_receipt_replace_user_by_trigram_hr/readme/DESCRIPTION.rst
odoo/addons/pos_receipt_replace_user_by_trigram_hr/static/description/icon.png
odoo/addons/pos_receipt_replace_user_by_trigram_hr/static/description/index.html
odoo_addon_pos_receipt_replace_user_by_trigram_hr-16.0.1.0.1.dist-info/METADATA
odoo_addon_pos_receipt_replace_user_by_trigram_hr-16.0.1.0.1.dist-info/WHEEL
odoo_addon_pos_receipt_replace_user_by_trigram_hr-16.0.1.0.1.dist-info/top_level.txt
odoo_addon_pos_receipt_replace_user_by_trigram_hr-16.0.1.0.1.dist-info/RECORD
